{"version":3,"value":{"basics\\Extensions.shared.kt":{"path":"basics\\Extensions.shared.kt","hash":"bcd123d24643dbce3404e14f1db599f3","data":{"interfaces":{},"declarations":{"div":"basics\\Extensions.shared","doubleAdd":"basics\\Extensions.shared","MyInteger":"basics\\Extensions.shared","half":"basics\\Extensions.shared","double":"basics\\Extensions.shared","main":"basics\\Extensions.shared"}}},"basics\\Numbers.shared.kt":{"path":"basics\\Numbers.shared.kt","hash":"5581de36d94f4c54e1da28f00306978b","data":{"interfaces":{},"declarations":{"main":"basics\\Numbers.shared"}}},"basics\\Weak.shared.kt":{"path":"basics\\Weak.shared.kt","hash":"6e0036f0141f60e5a2a29f3c58e23c10","data":{"interfaces":{},"declarations":{"SillyBox":"basics\\Weak.shared"}}},"basics\\When.shared.kt":{"path":"basics\\When.shared.kt","hash":"fbd94e58d91d0b01ed163967a4b59246","data":{"interfaces":{},"declarations":{"main":"basics\\When.shared"}}},"basics\\Typealias.shared.kt":{"path":"basics\\Typealias.shared.kt","hash":"91361e3c199d52421c7020a060f69c56","data":{"interfaces":{},"declarations":{"MyInteger":"basics\\Typealias.shared","Thing":"basics\\Typealias.shared"}}},"basics\\EscapingLambdas.shared.kt":{"path":"basics\\EscapingLambdas.shared.kt","hash":"690d3b7f6f221b2896506304050a449b","data":{"interfaces":{},"declarations":{"HasLambda":"basics\\EscapingLambdas.shared"}}},"basics\\IfExpressions.shared.kt":{"path":"basics\\IfExpressions.shared.kt","hash":"1169223107c0ebd1460f5983b73ff263","data":{"interfaces":{},"declarations":{"main":"basics\\IfExpressions.shared"}}},"basics\\Generics.shared.kt":{"path":"basics\\Generics.shared.kt","hash":"4fa11fe4aa844fa21a54e0635564517d","data":{"interfaces":{},"declarations":{"NameTag":"basics\\Generics.shared"}}},"basics\\Lambdas.shared.kt":{"path":"basics\\Lambdas.shared.kt","hash":"6644782e8214080769f1c1312eb0c4b4","data":{"interfaces":{},"declarations":{"main":"basics\\Lambdas.shared"}}},"basics\\Interface.shared.kt":{"path":"basics\\Interface.shared.kt","hash":"5a8fa5835b3b0f2f34232d71da538d65","data":{"interfaces":{"com.test.MyInterface":{"packageName":"com.test","name":"MyInterface","methods":["y"],"properties":["x"],"implements":[]}},"declarations":{"MyInterface":"basics\\Interface.shared","ImplOverX":"basics\\Interface.shared"}}},"basics\\StringInterpolation.shared.kt":{"path":"basics\\StringInterpolation.shared.kt","hash":"e8e8058e5a7f69c32669975f45f41e65","data":{"interfaces":{},"declarations":{"main":"basics\\StringInterpolation.shared"}}},"basics\\WhileLoop.shared.kt":{"path":"basics\\WhileLoop.shared.kt","hash":"f382981e7fcd889cf40df7d20bfa724c","data":{"interfaces":{},"declarations":{"main":"basics\\WhileLoop.shared"}}},"basics\\ComplexGenerics.shared.kt":{"path":"basics\\ComplexGenerics.shared.kt","hash":"4d43809bb45cedc556239cb2dd2a78c3","data":{"interfaces":{},"declarations":{"NameTag":"basics\\ComplexGenerics.shared"}}},"basics\\Maps.shared.kt":{"path":"basics\\Maps.shared.kt","hash":"b3a7d697789a17ca4f340d7b3001f9b1","data":{"interfaces":{},"declarations":{"main":"basics\\Maps.shared"}}},"basics\\NormalClass.shared.kt":{"path":"basics\\NormalClass.shared.kt","hash":"326370049c3f73a7440c5c9c06809fd3","data":{"interfaces":{},"declarations":{"Record":"basics\\NormalClass.shared"}}},"basics\\SafeAccess.shared.kt":{"path":"basics\\SafeAccess.shared.kt","hash":"99ba638541937d5ded8f9fa9878ac59c","data":{"interfaces":{},"declarations":{"SillyBox":"basics\\SafeAccess.shared"}}},"basics\\DataClasses.shared.kt":{"path":"basics\\DataClasses.shared.kt","hash":"30145e1cb936327eaebe9e53b64c692c","data":{"interfaces":{},"declarations":{"Record":"basics\\DataClasses.shared"}}},"basics\\ExtendClass.shared.kt":{"path":"basics\\ExtendClass.shared.kt","hash":"6cc3276f15ac183552c493d683e7c522","data":{"interfaces":{},"declarations":{"Record":"basics\\ExtendClass.shared"}}},"basics\\IfStatements.shared.kt":{"path":"basics\\IfStatements.shared.kt","hash":"ae8124d536ec699287dc4813b6708052","data":{"interfaces":{},"declarations":{"main":"basics\\IfStatements.shared"}}},"basics\\ForLoop.shared.kt":{"path":"basics\\ForLoop.shared.kt","hash":"3e2b5d55af735d004c83b6d30f8f14d0","data":{"interfaces":{},"declarations":{"main":"basics\\ForLoop.shared"}}},"basics\\Unowned.shared.kt":{"path":"basics\\Unowned.shared.kt","hash":"761196e98148f058e1292101367bbbe0","data":{"interfaces":{},"declarations":{"Thing":"basics\\Unowned.shared"}}},"basics\\CompanionObject.shared.kt":{"path":"basics\\CompanionObject.shared.kt","hash":"4e4dea1836909b69be8c84e3ba098781","data":{"interfaces":{},"declarations":{"Record":"basics\\CompanionObject.shared"}}},"basics\\HelloWorld.shared.kt":{"path":"basics\\HelloWorld.shared.kt","hash":"ff5a2d6b4f7d82199f2c63f616ba075c","data":{"interfaces":{},"declarations":{"main":"basics\\HelloWorld.shared"}}},"basics\\Functions.shared.kt":{"path":"basics\\Functions.shared.kt","hash":"780fe78754e01e1ea2477c1df1fc298c","data":{"interfaces":{},"declarations":{"addNumbers2":"basics\\Functions.shared","addNumbers":"basics\\Functions.shared","addNumbers3":"basics\\Functions.shared","main":"basics\\Functions.shared"}}},"basics\\AdvancedCasting.shared.kt":{"path":"basics\\AdvancedCasting.shared.kt","hash":"95e30a624a3d1d312e369f02ceecbefa","data":{"interfaces":{"com.test.AdvancedCastingTestInterface":{"packageName":"com.test","name":"AdvancedCastingTestInterface","methods":[],"properties":[],"implements":[]}},"declarations":{"AdvancedCastingTestImplementation":"basics\\AdvancedCasting.shared","AdvancedCastingTestInterface":"basics\\AdvancedCasting.shared"}}},"basics\\Object.shared.kt":{"path":"basics\\Object.shared.kt","hash":"2780673a1c0e10ade2f120dd50ef186a","data":{"interfaces":{},"declarations":{"Singleton":"basics\\Object.shared","main":"basics\\Object.shared"}}},"basics\\Casting.shared.kt":{"path":"basics\\Casting.shared.kt","hash":"6940c216f2532c0425c86ab33f3452f0","data":{"interfaces":{},"declarations":{"main":"basics\\Casting.shared"}}}}}